{
    "mask": [
        {
            "x": -3,
            "y": -3,
            "intensity": 0.21861314848560165
        },
        {
            "x": -3,
            "y": -2,
            "intensity": 0.36283984570750105
        },
        {
            "x": -3,
            "y": -1,
            "intensity": 0.20291353456531191
        },
        {
            "x": -3,
            "y": 0,
            "intensity": 0.14965000575957277
        },
        {
            "x": -3,
            "y": 1,
            "intensity": 0.7457843852912561
        },
        {
            "x": -3,
            "y": 2,
            "intensity": 0.9280418160337137
        },
        {
            "x": -3,
            "y": 3,
            "intensity": 0.2571796810099387
        },
        {
            "x": -2,
            "y": -3,
            "intensity": 0.8290613387101171
        },
        {
            "x": -2,
            "y": -2,
            "intensity": 0.7301783562426
        },
        {
            "x": -2,
            "y": -1,
            "intensity": 0.695618456062284
        },
        {
            "x": -2,
            "y": 0,
            "intensity": 0.028508605631512918
        },
        {
            "x": -2,
            "y": 1,
            "intensity": 0.18459091667917915
        },
        {
            "x": -2,
            "y": 2,
            "intensity": 0.20229970850845624
        },
        {
            "x": -2,
            "y": 3,
            "intensity": 0.1885501944874859
        },
        {
            "x": -1,
            "y": -3,
            "intensity": 0.440677103435382
        },
        {
            "x": -1,
            "y": -2,
            "intensity": 0.0390527532696372
        },
        {
            "x": -1,
            "y": -1,
            "intensity": 0.2390593837480769
        },
        {
            "x": -1,
            "y": 0,
            "intensity": 0.9836247217368572
        },
        {
            "x": -1,
            "y": 1,
            "intensity": 0.8039039935251979
        },
        {
            "x": -1,
            "y": 2,
            "intensity": 0.05793689707462746
        },
        {
            "x": -1,
            "y": 3,
            "intensity": 0.982911894912433
        },
        {
            "x": 0,
            "y": -3,
            "intensity": 0.3995052893980364
        },
        {
            "x": 0,
            "y": -2,
            "intensity": 0.7046886221200725
        },
        {
            "x": 0,
            "y": -1,
            "intensity": 0.8564769965146812
        },
        {
            "x": 0,
            "y": 0,
            "intensity": 0.16454867620033164
        },
        {
            "x": 0,
            "y": 1,
            "intensity": 0.16220962722300492
        },
        {
            "x": 0,
            "y": 2,
            "intensity": 0.6941427967272097
        },
        {
            "x": 0,
            "y": 3,
            "intensity": 0.09158980881035239
        },
        {
            "x": 1,
            "y": -3,
            "intensity": 0.3091100039364225
        },
        {
            "x": 1,
            "y": -2,
            "intensity": 0.6471503641619416
        },
        {
            "x": 1,
            "y": -1,
            "intensity": 0.5138601245238842
        },
        {
            "x": 1,
            "y": 0,
            "intensity": 0.09145144207928935
        },
        {
            "x": 1,
            "y": 1,
            "intensity": 0.7443538750154519
        },
        {
            "x": 1,
            "y": 2,
            "intensity": 0.3369284798792681
        },
        {
            "x": 1,
            "y": 3,
            "intensity": 0.3024688902307149
        },
        {
            "x": 2,
            "y": -3,
            "intensity": 0.006139278045687924
        },
        {
            "x": 2,
            "y": -2,
            "intensity": 0.2489474171637437
        },
        {
            "x": 2,
            "y": -1,
            "intensity": 0.20535888961922288
        },
        {
            "x": 2,
            "y": 0,
            "intensity": 0.21136540985832253
        },
        {
            "x": 2,
            "y": 1,
            "intensity": 0.42468263524857874
        },
        {
            "x": 2,
            "y": 2,
            "intensity": 0.680022596826015
        },
        {
            "x": 2,
            "y": 3,
            "intensity": 0.8407470829308419
        },
        {
            "x": 3,
            "y": -3,
            "intensity": 0.1247269635941568
        },
        {
            "x": 3,
            "y": -2,
            "intensity": 0.8970293138346159
        },
        {
            "x": 3,
            "y": -1,
            "intensity": 0.2013643780861647
        },
        {
            "x": 3,
            "y": 0,
            "intensity": 0.25522493460958173
        },
        {
            "x": 3,
            "y": 1,
            "intensity": 0.7267547085913468
        },
        {
            "x": 3,
            "y": 2,
            "intensity": 0.8238490342070006
        },
        {
            "x": 3,
            "y": 3,
            "intensity": 0.7970768296338304
        }
    ]
}